auto_snorkel/__init__.py
auto_snorkel/default_api.py
auto_snorkel/default_api_define.py
auto_snorkel/label_function.py
auto_snorkel/lf_analysis.py
auto_snorkel/lf_applier.py
auto_snorkel/lf_utils.py
auto_snorkel/query.py
auto_snorkel/query_applier.py
auto_snorkel/query_utils.py
auto_snorkel-1.0.dist-info/LICENSE
auto_snorkel-1.0.dist-info/METADATA
auto_snorkel-1.0.dist-info/WHEEL
auto_snorkel-1.0.dist-info/top_level.txt
auto_snorkel-1.0.dist-info/RECORD
