Metadata-Version: 2.1
Name: auto-snorkel
Version: 1.0
Summary: An open source toolkit for automatically generating labeling functions by language model.
Home-page: https://github.com/yilinearth/auto_snorkel-maskter
Author: Yilin Lu
Author-email: 22121281@zju.edu.cn
License: UNKNOWN
Platform: UNKNOWN
Classifier: Programming Language :: Python :: 3.8
Classifier: License :: OSI Approved :: MIT License
License-File: LICENSE
Requires-Dist: numpy (==1.18.5)
Requires-Dist: sklearn (==0.22.1)
Requires-Dist: openai
